README.rst
setup.py
precious/__init__.py
precious/helpers.py
precious/value.py
precious.egg-info/PKG-INFO
precious.egg-info/SOURCES.txt
precious.egg-info/dependency_links.txt
precious.egg-info/top_level.txt