Metadata-Version: 1.1
Name: precious
Version: 0.1.1
Summary: Value objects for Python
Home-page: https://github.com/biern/precious
Author: Marcin Biernat
Author-email: mb@marcinbiernat.pl
License: UNKNOWN
Platform: UNKNOWN
Classifier: Development Status :: 2 - Pre-Alpha
Classifier: Programming Language :: Python :: 3
Classifier: Programming Language :: Python :: 3.4
Classifier: Programming Language :: Python :: 3.5
